{ "columns":46,
 "image":"..\/spritesheets\/towerDefense_tilesheet.png",
 "imageheight":832,
 "imagewidth":1472,
 "margin":0,
 "name":"TexturedSpritesheet",
 "spacing":0,
 "tilecount":1196,
 "tileheight":32,
 "tileproperties":
    {
     "1000":
        {
         "hp":1500,
         "name":"ground_3",
         "velocity":200
        },
     "1001":
        {
         "hp":1500,
         "name":"ground_3",
         "velocity":200
        },
     "1002":
        {
         "hp":5000,
         "name":"ground_4",
         "velocity":50
        },
     "1003":
        {
         "hp":5000,
         "name":"ground_4",
         "velocity":50
        },
     "950":
        {
         "hp":1000,
         "name":"ground_1",
         "velocity":100
        },
     "951":
        {
         "hp":"1000",
         "name":"ground_1",
         "velocity":"100"
        },
     "952":
        {
         "hp":2000,
         "name":"ground_2",
         "velocity":100
        },
     "953":
        {
         "hp":2000,
         "name":"ground_2",
         "velocity":100
        },
     "954":
        {
         "hp":1500,
         "name":"ground_3",
         "velocity":200
        },
     "955":
        {
         "hp":1500,
         "name":"ground_3",
         "velocity":200
        },
     "956":
        {
         "hp":5000,
         "name":"ground_4",
         "velocity":50
        },
     "957":
        {
         "hp":5000,
         "name":"ground_4",
         "velocity":50
        },
     "996":
        {
         "hp":1000,
         "name":"ground_1",
         "velocity":100
        },
     "997":
        {
         "hp":1000,
         "name":"ground_1",
         "velocity":100
        },
     "998":
        {
         "hp":2000,
         "name":"ground_2",
         "velocity":100
        },
     "999":
        {
         "hp":2000,
         "name":"ground_2",
         "velocity":100
        }
    },
 "tilepropertytypes":
    {
     "1000":
        {
         "hp":"int",
         "name":"string",
         "velocity":"int"
        },
     "1001":
        {
         "hp":"int",
         "name":"string",
         "velocity":"int"
        },
     "1002":
        {
         "hp":"int",
         "name":"string",
         "velocity":"int"
        },
     "1003":
        {
         "hp":"int",
         "name":"string",
         "velocity":"int"
        },
     "950":
        {
         "hp":"int",
         "name":"string",
         "velocity":"int"
        },
     "951":
        {
         "hp":"string",
         "name":"string",
         "velocity":"string"
        },
     "952":
        {
         "hp":"int",
         "name":"string",
         "velocity":"int"
        },
     "953":
        {
         "hp":"int",
         "name":"string",
         "velocity":"int"
        },
     "954":
        {
         "hp":"int",
         "name":"string",
         "velocity":"int"
        },
     "955":
        {
         "hp":"int",
         "name":"string",
         "velocity":"int"
        },
     "956":
        {
         "hp":"int",
         "name":"string",
         "velocity":"int"
        },
     "957":
        {
         "hp":"int",
         "name":"string",
         "velocity":"int"
        },
     "996":
        {
         "hp":"int",
         "name":"string",
         "velocity":"int"
        },
     "997":
        {
         "hp":"int",
         "name":"string",
         "velocity":"int"
        },
     "998":
        {
         "hp":"int",
         "name":"string",
         "velocity":"int"
        },
     "999":
        {
         "hp":"int",
         "name":"string",
         "velocity":"int"
        }
    },
 "tiles":
    {
     "1000":
        {
         "type":"ground"
        },
     "1001":
        {
         "type":"ground"
        },
     "1002":
        {
         "type":"ground"
        },
     "1003":
        {
         "type":"ground"
        },
     "950":
        {
         "type":"ground"
        },
     "951":
        {
         "type":"ground"
        },
     "952":
        {
         "type":"ground"
        },
     "953":
        {
         "type":"ground"
        },
     "954":
        {
         "type":"ground"
        },
     "955":
        {
         "type":"ground"
        },
     "956":
        {
         "type":"ground"
        },
     "957":
        {
         "type":"ground"
        },
     "996":
        {
         "type":"ground"
        },
     "997":
        {
         "type":"ground"
        },
     "998":
        {
         "type":"ground"
        },
     "999":
        {
         "type":"ground"
        }
    },
 "tilewidth":32,
 "type":"tileset"
}